Metadata-Version: 2.1
Name: django-likeit-ptbr
Version: 0.1.1
Summary: UNKNOWN
Home-page: https://github.com/gustavodesc/django-likeit-ptbr
Author: Gustavo Guella
Author-email: gustavodesc@gmail.com
License: MIT License
Download-URL: https://github.com/gustavodesc/django-likeit-ptbr/tarball/0.1
Platform: UNKNOWN
Classifier: Environment :: Web Environment
Classifier: Framework :: Django
Classifier: Intended Audience :: Developers
Classifier: License :: OSI Approved :: MIT License
Classifier: Operating System :: OS Independent
Classifier: Programming Language :: Python
Classifier: Programming Language :: Python :: 3.5
Classifier: Programming Language :: Python :: 3.6
Classifier: Topic :: Internet :: WWW/HTTP
Classifier: Topic :: Internet :: WWW/HTTP :: Dynamic Content
